{"name":"Kewjs","tagline":"Kew is a lightweight alternative to jQuery selectors.","body":"# Usage\r\n\r\n## Initialize kew.js\r\n\r\nInclude the library in your page\r\n```javascript\r\n    <script src=\"path/to/kew.js\"></script>\r\n```\r\n\r\n## 1. Document ready\r\n```javascript\r\n    $.ready(function(){\r\n        // code to be executed after document has loaded\r\n    });\r\n```\r\n\r\n## 2. Query Selector\r\n```javascript\r\n    $.get('css selector').function();\r\n```\r\n`$.get()` has a few functions:\r\n* `list()`\r\n    - returns an array of elements\r\n* `first()`\r\n    - returns the first element\r\n* `each(function(el))`\r\n    - loops through the array of elements\r\n\r\n```javascript\r\n    // list()\r\n    var allDivs = $.get('div').list();\r\n    \r\n    // first()\r\n    var logoEl = $.get('#logo').first();\r\n\r\n    // each()\r\n    $.get('div').each(function(el) {\r\n        el.style.color = 'red';\r\n    });\r\n\r\n```\r\n","google":"UA-62943049-2","note":"Don't delete this file! It's used internally to help with page regeneration."}